<?xml version="1.0" encoding="utf-8" ?><dwsync><file name="fetch_meme.js.i" server="50.63.120.1" local="3428097000" remote="20607966184" /><file name="~2e_d_s___store.i" server="50.63.120.1" local="3428097000" remote="20607966184" /><file name="fetch_tweet.js.i" server="50.63.120.1" local="3428097000" remote="20607966184" /><file name="infinite_scroller_logic.js.i" server="50.63.120.1" local="3428097000" remote="20607966184" /><file name="fetch_meme.js.i" server="eatme.me" local="3428097000" remote="12018186152" /><file name="fetch_tweet.js.i" server="eatme.me" local="3428097000" remote="12018186152" /><file name="infinite_scroller_logic.js.i" server="eatme.me" local="3428097000" remote="12018186152" /><file name="~2e_d_s___store.i" server="eatme.me" local="3428097000" remote="12018186152" /></dwsync>